toyml/__init__.py
toyml/exception.py
toyml/py.typed
toyml/classification/__init__.py
toyml/classification/knn.py
toyml/clustering/__init__.py
toyml/clustering/agnes.py
toyml/clustering/bisect_kmeans.py
toyml/clustering/dbscan.py
toyml/clustering/kmeans.py
toyml/ensemble/__init__.py
toyml/ensemble/adaboost.py
toyml/ensemble/iforest.py
toyml-0.4.0.dist-info/LICENSE
toyml-0.4.0.dist-info/METADATA
toyml-0.4.0.dist-info/WHEEL
toyml-0.4.0.dist-info/top_level.txt
toyml-0.4.0.dist-info/zip-safe
toyml-0.4.0.dist-info/RECORD
