Metadata-Version: 2.1
Name: toyml
Version: 0.4.0
Summary: ToyML: Machine Learning from Scratch
Author-email: Xiangzhuang Shen <datahonor@gmail.com>
License: Apache 2.0
Project-URL: Homepage, https://github.com/ai-glimpse/toyml
Project-URL: Bug Tracker, https://github.com/ai-glimpse/toyml/issues
Project-URL: Documentation, https://ai-glimpse.github.io/toyml/
Project-URL: Source Code, https://github.com/ai-glimpse/toyml
Project-URL: Release Notes, https://ai-glimpse.github.io/toyml/changelog/
Keywords: machine learning,statistics,engineering
Classifier: Development Status :: 3 - Alpha
Classifier: Intended Audience :: Science/Research
Classifier: Intended Audience :: Developers
Classifier: License :: OSI Approved :: Apache Software License
Classifier: Operating System :: OS Independent
Classifier: Programming Language :: Python :: 3.10
Classifier: Programming Language :: Python :: 3.11
Classifier: Programming Language :: Python :: 3.12
Classifier: Programming Language :: Python :: 3.13
Classifier: Programming Language :: Python :: Implementation :: CPython
Classifier: Topic :: Scientific/Engineering
Classifier: Topic :: Scientific/Engineering :: Mathematics
Requires-Python: >=3.10
License-File: LICENSE
Provides-Extra: dev
Requires-Dist: pre-commit ; extra == 'dev'
Requires-Dist: ipython ; extra == 'dev'
Requires-Dist: black ; extra == 'dev'
Requires-Dist: flake8 ; extra == 'dev'
Requires-Dist: mypy ; extra == 'dev'
Requires-Dist: isort ; extra == 'dev'
Requires-Dist: ruff ; extra == 'dev'
Requires-Dist: pytest ; extra == 'dev'
Requires-Dist: pytest-cov ; extra == 'dev'
Requires-Dist: hypothesis >=6.112.0 ; extra == 'dev'
Provides-Extra: docs
Requires-Dist: mkdocs ; extra == 'docs'
Requires-Dist: mkdocs-material ; extra == 'docs'
Requires-Dist: mkdocs-material-extensions ; extra == 'docs'
Requires-Dist: mkdocs-bibtex ; extra == 'docs'
Requires-Dist: mkdocstrings-python ; extra == 'docs'
Requires-Dist: mkdocs-autorefs ; extra == 'docs'
Requires-Dist: mkdocs-git-committers-plugin-2 ; extra == 'docs'
Requires-Dist: mkdocs-git-revision-date-localized-plugin ; extra == 'docs'
Provides-Extra: plot
Requires-Dist: matplotlib ; extra == 'plot'
Requires-Dist: networkx ; extra == 'plot'
Requires-Dist: scipy ; extra == 'plot'
